{
  "DataStartingRow": 0,
  "ColumnHeader": {
    "Name": {
      "Value": "យឿន ជុំ",
      "Label": "Name",
      "Rules": [
        {
          "Required": false
        }
      ],
      "Format": "string",
      "Message": "Cell required value."
    },
    "Village": {
      "Value": "ត្របែក",
      "Label": "Village",
      "Rules": [
        {
          "Required": false
        }
      ],
      "Format": "string",
      "Message": "Cell required value."
    },
    "Money": {
      "Value": "ថវិកា",
      "Label": "Money",
      "Rules": [
        {
          "Required": false
        }
      ],
      "Format": "string",
      "Message": "Cell required value."
    }
  }
}
